scu_jwc_toolkit/__init__.py
scu_jwc_toolkit/gradeUtils.py
scu_jwc_toolkit/config/__init__.py
scu_jwc_toolkit/config/connectionConfig.py
scu_jwc_toolkit/config/headerConfig.py
scu_jwc_toolkit/config/loginConfig.py
scu_jwc_toolkit/entity/__init__.py
scu_jwc_toolkit/entity/exam.py
scu_jwc_toolkit/entity/gradeRecord.py
scu_jwc_toolkit/entity/score.py
scu_jwc_toolkit/exceptions/__init__.py
scu_jwc_toolkit/exceptions/loginException.py
scu_jwc_toolkit/parser/__init__.py
scu_jwc_toolkit/parser/curriculumParser.py
scu_jwc_toolkit/parser/gradeParser.py
scu_jwc_toolkit/providers/__init__.py
scu_jwc_toolkit/providers/auth/__init__.py
scu_jwc_toolkit/providers/auth/rememberTokenProvider.py
scu_jwc_toolkit/providers/auth/sessionidLoginProvider.py
scu_jwc_toolkit/providers/auth/smartLoginProvider.py
scu_jwc_toolkit/providers/auth/usernameLoginProvider.py
scu_jwc_toolkit/providers/curriculum/__init__.py
scu_jwc_toolkit/providers/curriculum/curriculcumProvider.py
scu_jwc_toolkit/providers/grade/__init__.py
scu_jwc_toolkit/providers/grade/gradeProvider.py
scu_jwc_toolkit/utils/__init__.py
scu_jwc_toolkit/utils/login_check.py
scu_jwc_unofficial_toolkit-0.0.1.dist-info/LICENSE
scu_jwc_unofficial_toolkit-0.0.1.dist-info/METADATA
scu_jwc_unofficial_toolkit-0.0.1.dist-info/WHEEL
scu_jwc_unofficial_toolkit-0.0.1.dist-info/top_level.txt
scu_jwc_unofficial_toolkit-0.0.1.dist-info/RECORD
