Metadata-Version: 2.1
Name: scu-jwc-unofficial-toolkit
Version: 0.0.1
Summary: An unofficial toolkit for scu jwc
Home-page: https://github.com/KXXH/SCU_JWC_toolkit
Author: KXXH
Author-email: zjm97@outlook.com
License: UNKNOWN
Platform: UNKNOWN
Classifier: Programming Language :: Python :: 3
Classifier: License :: OSI Approved :: MIT License
Classifier: Operating System :: OS Independent
Requires-Dist: requests
Requires-Dist: icalendar
